wowool/apps/contact_info/__init__.py
wowool/apps/contact_info/app_id.py
wowool/apps/contact_info/config.py
wowool/apps/contact_info/contact_info.py
wowool_contact_info-2.1.1.dist-info/METADATA
wowool_contact_info-2.1.1.dist-info/WHEEL
wowool_contact_info-2.1.1.dist-info/top_level.txt
wowool_contact_info-2.1.1.dist-info/RECORD
