Metadata-Version: 2.4
Name: wowool-contact-info
Version: 2.1.1
Summary: The Wowool Contact Info Package
Home-page: https://www.wowool.com/
Author: Wowool
Author-email: info@wowool.com
Requires-Python: >=3.11
Dynamic: author
Dynamic: author-email
Dynamic: description
Dynamic: home-page
Dynamic: requires-python
Dynamic: summary
